find_dot_aryo/__init__.py
find_dot_aryo/find_dot.py
find_dot_aryo-0.0.2.dist-info/METADATA
find_dot_aryo-0.0.2.dist-info/WHEEL
find_dot_aryo-0.0.2.dist-info/licenses/LICENSE
find_dot_aryo-0.0.2.dist-info/RECORD
